email_me_anything/__init__.py
email_me_anything/config.py
email_me_anything/csvutils.py
email_me_anything/emailutils.py
email_me_anything/luckyemail.py
email_me_anything-0.2.3.dist-info/licenses/LICENSE
email_me_anything-0.2.3.dist-info/METADATA
email_me_anything-0.2.3.dist-info/WHEEL
email_me_anything-0.2.3.dist-info/RECORD
