Metadata-Version: 2.4
Name: email_me_anything
Version: 0.2.3
Summary: Send emails programmatically with a simple Python interface
License-Expression: Apache-2.0
License-File: LICENSE
Keywords: email,automation,mail,python,api
Author: Shreyas Ashtamkar
Author-email: 51398602+Shreyas-Ashtamkar@users.noreply.github.com
Requires-Python: >=3.10,<4.0
Classifier: Programming Language :: Python :: 3
Classifier: Programming Language :: Python :: 3.12
Classifier: License :: OSI Approved :: Apache Software License
Classifier: Operating System :: OS Independent
Classifier: Intended Audience :: Developers
Classifier: Topic :: Communications :: Email
Requires-Dist: mailersend (>=2.0.0,<3.0.0)
Requires-Dist: python-dotenv (>=1.2.1,<2.0.0)
